vpsman/__init__.py
vpsman/cli.py
vpsman/core/__init__.py
vpsman/core/users.py
vpsman-0.1.2.dist-info/LICENSE
vpsman-0.1.2.dist-info/METADATA
vpsman-0.1.2.dist-info/WHEEL
vpsman-0.1.2.dist-info/entry_points.txt
vpsman-0.1.2.dist-info/top_level.txt
vpsman-0.1.2.dist-info/RECORD
