Metadata-Version: 2.1
Name: vpsman
Version: 0.1.2
Summary: A VPS management tool
Home-page: https://github.com/mason-webmaster/vpsman
Author: mason_dev
Author-email: websong16@gmail.com
Classifier: Programming Language :: Python :: 3
Classifier: License :: OSI Approved :: MIT License
Classifier: Operating System :: OS Independent
Requires-Python: >=3.6
License-File: LICENSE
Requires-Dist: questionary >=1.10.0
